collective.sticky-1.1.2-py2.7-nspkg.pth
collective/sticky/__init__.py
collective/sticky/behavior.py
collective/sticky/collection.py
collective/sticky/configure.zcml
collective/sticky/extender.py
collective/sticky/interfaces.py
collective/sticky/sticky_summary_collection_view.pt
collective/sticky/sticky_summary_topic_view.pt
collective/sticky/testing.py
collective/sticky/testing.zcml
collective/sticky/upgrades.py
collective/sticky/locales/collective.sticky.pot
collective/sticky/locales/manual.pot
collective/sticky/locales/fr/LC_MESSAGES/collective.sticky.po
collective/sticky/profiles/default/browserlayer.xml
collective/sticky/profiles/default/catalog.xml
collective/sticky/profiles/default/metadata.xml
collective/sticky/profiles/default/portal_atct.xml
collective/sticky/profiles/default/registry.xml
collective/sticky/profiles/default/types/Collection.xml
collective/sticky/profiles/uninstall/browserlayer.xml
collective/sticky/profiles/uninstall/catalog.xml
collective/sticky/profiles/uninstall/portal_atct.xml
collective/sticky/profiles/uninstall/registry.xml
collective/sticky/profiles/uninstall/types/Collection.xml
collective/sticky/tests/__init__.py
collective/sticky/tests/test_behavior.py
collective/sticky/tests/test_setup.py
collective.sticky-1.1.2.dist-info/DESCRIPTION.rst
collective.sticky-1.1.2.dist-info/METADATA
collective.sticky-1.1.2.dist-info/RECORD
collective.sticky-1.1.2.dist-info/WHEEL
collective.sticky-1.1.2.dist-info/metadata.json
collective.sticky-1.1.2.dist-info/namespace_packages.txt
collective.sticky-1.1.2.dist-info/top_level.txt
