Metadata-Version: 2.0
Name: collective.sticky
Version: 1.1.2
Summary: Collective sticky package
Home-page: http://github.com/imio/
Author: 
Author-email: 
License: GPL
Keywords: Plone Zope Sticky
Platform: UNKNOWN
Classifier: Framework :: Plone
Classifier: Programming Language :: Python
Classifier: Topic :: Software Development :: Libraries :: Python Modules
Provides-Extra: test
Requires-Dist: setuptools
Requires-Dist: plone.api
Provides-Extra: test
Requires-Dist: plone.app.testing; extra == 'test'
